{
  "id": "fm-email-addresses-SiZhbXA7",
  "name": "email_addresses",
  "defaultTableOccurrence": "email_addresses",
  "canvas": {
    "width": 923,
    "height": 600,
    "gridSize": 8,
    "showGrid": false,
    "snapToGrid": false
  },
  "components": [
    {
      "id": "ddr-fm-email-addresses-SiZhbXA7-1",
      "position": {
        "x": 12,
        "y": 42,
        "width": 46.005,
        "height": 11,
        "z": 1
      },
      "props": {
        "styleTheme": "Classic",
        "ddrObjectPath": "1",
        "rotation": 0,
        "autosizeTop": true,
        "autosizeRight": false,
        "autosizeBottom": false,
        "autosizeLeft": true,
        "ddrOriginalObjectType": "Text",
        "ddrObjectFlags": 0,
        "ddrAnchorSource": "flags",
        "ddrStyleParsed": true,
        "ddrConditionalFormattingStatic": false,
        "ddrSourceTop": 42,
        "ddrSourceLeft": 12,
        "ddrSourceBottom": 53,
        "ddrSourceRight": 58.005,
        "fillType": "none",
        "lineColor": "rgba(0, 0, 0, 1)",
        "lineStyle": "solid",
        "effectOuterShadow": true,
        "fontSize": 9,
        "fontWeight": "bold",
        "fontFamily": "Helvetica",
        "textColor": "#000000",
        "label": "contactID",
        "ddrArrangeOrder": 1
      },
      "type": "label"
    },
    {
      "id": "ddr-fm-email-addresses-SiZhbXA7-6",
      "position": {
        "x": 127,
        "y": 42,
        "width": 70,
        "height": 11,
        "z": 2
      },
      "props": {
        "styleTheme": "Classic",
        "ddrObjectPath": "6",
        "rotation": 0,
        "autosizeTop": true,
        "autosizeRight": false,
        "autosizeBottom": false,
        "autosizeLeft": true,
        "ddrOriginalObjectType": "Text",
        "ddrObjectFlags": 0,
        "ddrAnchorSource": "flags",
        "ddrStyleParsed": true,
        "ddrConditionalFormattingStatic": false,
        "ddrSourceTop": 42,
        "ddrSourceLeft": 127,
        "ddrSourceBottom": 53,
        "ddrSourceRight": 197,
        "fillType": "none",
        "lineColor": "rgba(0, 0, 0, 1)",
        "lineStyle": "solid",
        "effectOuterShadow": true,
        "fontSize": 9,
        "fontWeight": "bold",
        "fontFamily": "Helvetica",
        "textColor": "#000000",
        "label": "Email_Address",
        "ddrArrangeOrder": 2
      },
      "type": "label"
    },
    {
      "id": "ddr-fm-email-addresses-SiZhbXA7-7",
      "position": {
        "x": 588,
        "y": 42,
        "width": 37.014,
        "height": 11,
        "z": 3
      },
      "props": {
        "styleTheme": "Classic",
        "ddrObjectPath": "7",
        "rotation": 0,
        "autosizeTop": true,
        "autosizeRight": false,
        "autosizeBottom": false,
        "autosizeLeft": true,
        "ddrOriginalObjectType": "Text",
        "ddrObjectFlags": 0,
        "ddrAnchorSource": "flags",
        "ddrStyleParsed": true,
        "ddrConditionalFormattingStatic": false,
        "ddrSourceTop": 42,
        "ddrSourceLeft": 588,
        "ddrSourceBottom": 53,
        "ddrSourceRight": 625.014,
        "fillType": "none",
        "lineColor": "rgba(0, 0, 0, 1)",
        "lineStyle": "solid",
        "effectOuterShadow": true,
        "fontSize": 9,
        "fontWeight": "bold",
        "fontFamily": "Helvetica",
        "textColor": "#000000",
        "label": "emailID",
        "ddrArrangeOrder": 3
      },
      "type": "label"
    },
    {
      "id": "ddr-fm-email-addresses-SiZhbXA7-8",
      "position": {
        "x": 695,
        "y": 42,
        "width": 82.01,
        "height": 11,
        "z": 4
      },
      "props": {
        "styleTheme": "Classic",
        "ddrObjectPath": "8",
        "rotation": 0,
        "autosizeTop": true,
        "autosizeRight": false,
        "autosizeBottom": false,
        "autosizeLeft": true,
        "ddrOriginalObjectType": "Text",
        "ddrObjectFlags": 0,
        "ddrAnchorSource": "flags",
        "ddrStyleParsed": true,
        "ddrConditionalFormattingStatic": false,
        "ddrSourceTop": 42,
        "ddrSourceLeft": 695,
        "ddrSourceBottom": 53,
        "ddrSourceRight": 777.01,
        "fillType": "none",
        "lineColor": "rgba(0, 0, 0, 1)",
        "lineStyle": "solid",
        "effectOuterShadow": true,
        "fontSize": 9,
        "fontWeight": "bold",
        "fontFamily": "Helvetica",
        "textColor": "#000000",
        "label": "modification_time",
        "ddrArrangeOrder": 4
      },
      "type": "label"
    },
    {
      "id": "ddr-fm-email-addresses-SiZhbXA7-9",
      "position": {
        "x": 793.01,
        "y": 42,
        "width": 58.007,
        "height": 11,
        "z": 5
      },
      "props": {
        "styleTheme": "Classic",
        "ddrObjectPath": "9",
        "rotation": 0,
        "autosizeTop": true,
        "autosizeRight": false,
        "autosizeBottom": false,
        "autosizeLeft": true,
        "ddrOriginalObjectType": "Text",
        "ddrObjectFlags": 0,
        "ddrAnchorSource": "flags",
        "ddrStyleParsed": true,
        "ddrConditionalFormattingStatic": false,
        "ddrSourceTop": 42,
        "ddrSourceLeft": 793.01,
        "ddrSourceBottom": 53,
        "ddrSourceRight": 851.017,
        "fillType": "none",
        "lineColor": "rgba(0, 0, 0, 1)",
        "lineStyle": "solid",
        "effectOuterShadow": true,
        "fontSize": 9,
        "fontWeight": "bold",
        "fontFamily": "Helvetica",
        "textColor": "#000000",
        "label": "modified_by",
        "ddrArrangeOrder": 5
      },
      "type": "label"
    },
    {
      "id": "ddr-fm-email-addresses-SiZhbXA7-10",
      "position": {
        "x": 12,
        "y": 66,
        "width": 106,
        "height": 14,
        "z": 6
      },
      "props": {
        "styleTheme": "Classic",
        "ddrObjectPath": "10",
        "rotation": 0,
        "autosizeTop": true,
        "autosizeRight": false,
        "autosizeBottom": false,
        "autosizeLeft": true,
        "ddrOriginalObjectType": "Field",
        "ddrObjectFlags": 0,
        "ddrAnchorSource": "flags",
        "ddrStyleParsed": true,
        "ddrConditionalFormattingStatic": false,
        "ddrSourceTop": 66,
        "ddrSourceLeft": 12,
        "ddrSourceBottom": 80,
        "ddrSourceRight": 118,
        "fillType": "none",
        "lineStyle": "none",
        "effectOuterShadow": true,
        "fontSize": 12,
        "textAlign": "center",
        "label": "",
        "labelPlacement": "none",
        "placeholder": "contactID",
        "controlType": "text",
        "showPlaceholderInFindMode": false,
        "repetitionsFrom": 1,
        "repetitionsTo": 1,
        "inputMethod": "Automatic",
        "keyboardType": "Default for Data Type",
        "includeInQuickFind": true,
        "ddrArrangeOrder": 6
      },
      "type": "field",
      "binding": {
        "field": "contactID",
        "tableOccurrence": "Email Addresses"
      }
    },
    {
      "id": "ddr-fm-email-addresses-SiZhbXA7-15",
      "position": {
        "x": 127,
        "y": 66,
        "width": 252,
        "height": 14,
        "z": 7
      },
      "props": {
        "styleTheme": "Classic",
        "ddrObjectPath": "15",
        "rotation": 0,
        "autosizeTop": true,
        "autosizeRight": false,
        "autosizeBottom": false,
        "autosizeLeft": true,
        "ddrOriginalObjectType": "Field",
        "ddrObjectFlags": 0,
        "ddrAnchorSource": "flags",
        "ddrStyleParsed": true,
        "ddrConditionalFormattingStatic": false,
        "ddrSourceTop": 66,
        "ddrSourceLeft": 127,
        "ddrSourceBottom": 80,
        "ddrSourceRight": 379,
        "fillType": "none",
        "lineStyle": "none",
        "effectOuterShadow": true,
        "fontSize": 12,
        "label": "",
        "labelPlacement": "none",
        "placeholder": "Email_Address",
        "controlType": "text",
        "showPlaceholderInFindMode": false,
        "repetitionsFrom": 1,
        "repetitionsTo": 1,
        "inputMethod": "Automatic",
        "keyboardType": "Default for Data Type",
        "includeInQuickFind": true,
        "ddrArrangeOrder": 7
      },
      "type": "field",
      "binding": {
        "field": "Email_Address",
        "tableOccurrence": "Email Addresses"
      }
    },
    {
      "id": "ddr-fm-email-addresses-SiZhbXA7-16",
      "position": {
        "x": 588,
        "y": 66,
        "width": 106,
        "height": 14,
        "z": 8
      },
      "props": {
        "styleTheme": "Classic",
        "ddrObjectPath": "16",
        "rotation": 0,
        "autosizeTop": true,
        "autosizeRight": false,
        "autosizeBottom": false,
        "autosizeLeft": true,
        "ddrOriginalObjectType": "Field",
        "ddrObjectFlags": 0,
        "ddrAnchorSource": "flags",
        "ddrStyleParsed": true,
        "ddrConditionalFormattingStatic": false,
        "ddrSourceTop": 66,
        "ddrSourceLeft": 588,
        "ddrSourceBottom": 80,
        "ddrSourceRight": 694,
        "fillType": "none",
        "lineStyle": "none",
        "effectOuterShadow": true,
        "fontSize": 12,
        "textAlign": "center",
        "label": "",
        "labelPlacement": "none",
        "placeholder": "emailID",
        "controlType": "text",
        "showPlaceholderInFindMode": false,
        "repetitionsFrom": 1,
        "repetitionsTo": 1,
        "inputMethod": "Automatic",
        "keyboardType": "Default for Data Type",
        "includeInQuickFind": true,
        "ddrArrangeOrder": 8
      },
      "type": "field",
      "binding": {
        "field": "emailID",
        "tableOccurrence": "Email Addresses"
      }
    },
    {
      "id": "ddr-fm-email-addresses-SiZhbXA7-17",
      "position": {
        "x": 695,
        "y": 66,
        "width": 97.01,
        "height": 14,
        "z": 9
      },
      "props": {
        "styleTheme": "Classic",
        "ddrObjectPath": "17",
        "rotation": 0,
        "autosizeTop": true,
        "autosizeRight": false,
        "autosizeBottom": false,
        "autosizeLeft": true,
        "ddrOriginalObjectType": "Field",
        "ddrObjectFlags": 0,
        "ddrAnchorSource": "flags",
        "ddrStyleParsed": true,
        "ddrConditionalFormattingStatic": false,
        "ddrSourceTop": 66,
        "ddrSourceLeft": 695,
        "ddrSourceBottom": 80,
        "ddrSourceRight": 792.01,
        "fillType": "none",
        "lineStyle": "none",
        "effectOuterShadow": true,
        "fontSize": 12,
        "textAlign": "center",
        "label": "",
        "labelPlacement": "none",
        "placeholder": "modification_time",
        "controlType": "text",
        "showPlaceholderInFindMode": false,
        "repetitionsFrom": 1,
        "repetitionsTo": 1,
        "inputMethod": "Automatic",
        "keyboardType": "Default for Data Type",
        "includeInQuickFind": true,
        "ddrArrangeOrder": 9
      },
      "type": "field",
      "binding": {
        "field": "modification_time",
        "tableOccurrence": "Email Addresses"
      }
    },
    {
      "id": "ddr-fm-email-addresses-SiZhbXA7-18",
      "position": {
        "x": 793.01,
        "y": 66,
        "width": 106,
        "height": 14,
        "z": 10
      },
      "props": {
        "styleTheme": "Classic",
        "ddrObjectPath": "18",
        "rotation": 0,
        "autosizeTop": true,
        "autosizeRight": false,
        "autosizeBottom": false,
        "autosizeLeft": true,
        "ddrOriginalObjectType": "Field",
        "ddrObjectFlags": 0,
        "ddrAnchorSource": "flags",
        "ddrStyleParsed": true,
        "ddrConditionalFormattingStatic": false,
        "ddrSourceTop": 66,
        "ddrSourceLeft": 793.01,
        "ddrSourceBottom": 80,
        "ddrSourceRight": 899.01,
        "fillType": "none",
        "lineStyle": "none",
        "effectOuterShadow": true,
        "fontSize": 12,
        "textAlign": "center",
        "label": "",
        "labelPlacement": "none",
        "placeholder": "modified_by",
        "controlType": "text",
        "showPlaceholderInFindMode": false,
        "repetitionsFrom": 1,
        "repetitionsTo": 1,
        "inputMethod": "Automatic",
        "keyboardType": "Default for Data Type",
        "includeInQuickFind": true,
        "ddrArrangeOrder": 10
      },
      "type": "field",
      "binding": {
        "field": "modified_by",
        "tableOccurrence": "Email Addresses"
      }
    }
  ],
  "actions": []
}